[
  {
    "id": 1001,
    "user_id": 1,
    "product_id": 1,
    "final_price": 15000,
    "status": "waiting_payment",
    "tanggal_dipesan": "2025-02-01T10:00:00",
    "tanggal_dibayar": null,
    "tanggal_selesai": null,
    "tanggal_dibatalkan": null,
    "form_data": {
      "uid": "809123456",
      "server": "Asia",
      "email": "user1@example.com",
      "phone": "081234567890"
    },
    "admin_log": []
  },
  {
    "id": 1002,
    "user_id": 2,
    "product_id": 2,
    "final_price": 75000,
    "status": "paid",
    "tanggal_dipesan": "2025-02-02T09:30:00",
    "tanggal_dibayar": "2025-02-02T09:45:00",
    "tanggal_selesai": null,
    "tanggal_dibatalkan": null,
    "form_data": {
      "uid": "802345678",
      "server": "Asia",
      "email": "user2@example.com",
      "phone": "082345678901"
    },
    "admin_log": []
  },
  {
    "id": 1003,
    "user_id": 1,
    "product_id": 3,
    "final_price": 250000,
    "status": "pending",
    "tanggal_dipesan": "2025-02-03T14:00:00",
    "tanggal_dibayar": "2025-02-03T14:10:00",
    "tanggal_selesai": null,
    "tanggal_dibatalkan": null,
    "form_data": {
      "uid": "804567890",
      "server": "Asia",
      "email": "user1@example.com",
      "phone": "081234567891"
    },
    "admin_log": []
  },
  {
    "id": 1004,
    "user_id": 2,
    "product_id": 4,
    "final_price": 16000,
    "status": "processing",
    "tanggal_dipesan": "2025-02-04T11:00:00",
    "tanggal_dibayar": "2025-02-04T11:20:00",
    "tanggal_selesai": null,
    "tanggal_dibatalkan": null,
    "form_data": {
      "uid": "806789012",
      "server": "Asia",
      "email": "user2@example.com",
      "phone": "082345678902"
    },
    "admin_log": [
      {
        "admin_id": 1,
        "status": "in_progress",
        "waktu_mulai": "2025-02-04T11:30:00",
        "waktu_selesai": null
      }
    ]
  }
]
